secret_ai_sdk/__init__.py
secret_ai_sdk/_client.py
secret_ai_sdk/_config.py
secret_ai_sdk/_enhanced_client.py
secret_ai_sdk/_retry.py
secret_ai_sdk/secret.py
secret_ai_sdk/secret_ai.py
secret_ai_sdk/secret_ai_ex.py
secret_ai_sdk/voice_secret.py
secret_ai_sdk-0.1.7.dist-info/licenses/LICENSE
secret_ai_sdk-0.1.7.dist-info/METADATA
secret_ai_sdk-0.1.7.dist-info/WHEEL
secret_ai_sdk-0.1.7.dist-info/top_level.txt
secret_ai_sdk-0.1.7.dist-info/RECORD
