Metadata-Version: 2.4
Name: secret-ai-sdk
Version: 0.1.7
Summary: Secret AI Confidential VM SDK - Python interface for Secret Network's confidential AI models
Author-email: Alex H <alexh@scrtlabs.com>
License: MIT License
Project-URL: Homepage, https://github.com/scrtlabs/secret-ai-sdk
Project-URL: Documentation, https://docs.scrt.network/secret-network-documentation/secret-ai/sdk
Project-URL: Repository, https://github.com/scrtlabs/secret-ai-sdk
Project-URL: Bug Reports, https://github.com/scrtlabs/secret-ai-sdk/issues
Project-URL: Secret Network, https://scrt.network
Keywords: secret-network,ai,confidential-computing,llm,privacy,blockchain,tts,stt
Classifier: Development Status :: 4 - Beta
Classifier: Intended Audience :: Developers
Classifier: License :: OSI Approved :: MIT License
Classifier: Operating System :: OS Independent
Classifier: Programming Language :: Python :: 3
Classifier: Programming Language :: Python :: 3.10
Classifier: Programming Language :: Python :: 3.11
Classifier: Programming Language :: Python :: 3.12
Classifier: Programming Language :: Python :: 3.13
Classifier: Topic :: Software Development :: Libraries :: Python Modules
Classifier: Topic :: Scientific/Engineering :: Artificial Intelligence
Classifier: Topic :: Security :: Cryptography
Requires-Python: >=3.10
License-File: LICENSE
Requires-Dist: aiohappyeyeballs>=2.4.0
Requires-Dist: aiohttp>=3.11.0
Requires-Dist: aiosignal>=1.3.0
Requires-Dist: annotated-types>=0.7.0
Requires-Dist: anyio>=4.7.0
Requires-Dist: attrs>=20.3.0
Requires-Dist: bech32>=1.2.0
Requires-Dist: betterproto>=2.0.0b5
Requires-Dist: bip32utils>=0.3.post4
Requires-Dist: boltons>=21.0.0
Requires-Dist: certifi>=2024.12.14
Requires-Dist: cffi>=1.17.0
Requires-Dist: charset-normalizer>=3.4.0
Requires-Dist: cryptography>=44.0.0
Requires-Dist: ecdsa>=0.16.0
Requires-Dist: frozenlist>=1.5.0
Requires-Dist: furl>=2.1.0
Requires-Dist: greenlet>=3.1.0
Requires-Dist: grpclib>=0.4.0
Requires-Dist: h11>=0.14.0
Requires-Dist: h2>=4.1.0
Requires-Dist: hpack>=4.0.0
Requires-Dist: httpcore>=1.0.0
Requires-Dist: httpx>=0.27.0
Requires-Dist: hyperframe>=6.0.0
Requires-Dist: idna>=3.10
Requires-Dist: jsonpatch>=1.33
Requires-Dist: jsonpointer>=3.0.0
Requires-Dist: langchain>=0.3.0
Requires-Dist: langchain-core>=0.3.0
Requires-Dist: langchain-ollama>=0.2.0
Requires-Dist: langchain-text-splitters>=0.3.0
Requires-Dist: langsmith>=0.2.0
Requires-Dist: miscreant>=0.3.0
Requires-Dist: mnemonic>=0.19
Requires-Dist: multidict>=6.1.0
Requires-Dist: nest-asyncio>=1.6.0
Requires-Dist: numpy>=2.0.0
Requires-Dist: ollama>=0.4.0
Requires-Dist: orderedmultidict>=1.0.0
Requires-Dist: orjson>=3.10.0
Requires-Dist: packaging>=24.0
Requires-Dist: propcache>=0.2.0
Requires-Dist: protobuf>=3.20.0
Requires-Dist: pycparser>=2.22
Requires-Dist: pydantic>=2.10.0
Requires-Dist: pydantic-core>=2.27.0
Requires-Dist: python-dateutil>=2.9.0
Requires-Dist: pyyaml>=6.0.0
Requires-Dist: requests>=2.32.0
Requires-Dist: requests-toolbelt>=1.0.0
Requires-Dist: secret-sdk>=1.8.1
Requires-Dist: setuptools>=75.0.0
Requires-Dist: six>=1.17.0
Requires-Dist: sniffio>=1.3.0
Requires-Dist: sqlalchemy>=2.0.0
Requires-Dist: tenacity>=9.0.0
Requires-Dist: typing-extensions>=4.12.0
Requires-Dist: urllib3>=2.2.0
Requires-Dist: wheel>=0.44.0
Requires-Dist: wrapt>=1.17.0
Requires-Dist: yarl>=1.18.0
Provides-Extra: dev
Requires-Dist: build>=1.0.0; extra == "dev"
Requires-Dist: twine>=4.0.0; extra == "dev"
Requires-Dist: pytest>=7.0.0; extra == "dev"
Requires-Dist: pytest-asyncio>=0.21.0; extra == "dev"
Requires-Dist: black>=23.0.0; extra == "dev"
Requires-Dist: ruff>=0.1.0; extra == "dev"
Dynamic: license-file
